east_money_worm_tools/__init__.py
east_money_worm_tools/basic_function_module.py
east_money_worm_tools-0.0.6.dist-info/METADATA
east_money_worm_tools-0.0.6.dist-info/WHEEL
east_money_worm_tools-0.0.6.dist-info/top_level.txt
east_money_worm_tools-0.0.6.dist-info/RECORD
