Metadata-Version: 2.1
Name: east-money-worm-tools
Version: 0.0.6
Summary: east_money_worm_tools
Home-page: UNKNOWN
Author: Peter Wang
Author-email: 2856954422@qq.com
License: UNKNOWN
Keywords: east_money_worm_tools
Platform: UNKNOWN
Classifier: Development Status :: 5 - Production/Stable
Classifier: Intended Audience :: Developers
Classifier: Programming Language :: Python :: 3
Classifier: Programming Language :: Python :: 3.4
Classifier: Programming Language :: Python :: 3.5
Classifier: Programming Language :: Python :: 3.6
Classifier: Programming Language :: Python :: 3.7
